pipiy/__init__.py
pipiy/pipiy.py
pipiy-0.2.5.dist-info/entry_points.txt
pipiy-0.2.5.dist-info/METADATA
pipiy-0.2.5.dist-info/WHEEL
pipiy-0.2.5.dist-info/RECORD
