Metadata-Version: 2.1
Name: pipiy
Version: 0.2.5
Summary: pipiy module manager
Home-page: https://github.com/lunastev/pipiy
Author: LunaStev
Author-email: lunastev@gurmstudios.com
Classifier: Programming Language :: Python :: 2
Classifier: Programming Language :: Python :: 2.7
Classifier: Programming Language :: Python :: 3
Classifier: Programming Language :: Python :: 3.4
Classifier: Programming Language :: Python :: 3.5
Classifier: Programming Language :: Python :: 3.6
Classifier: Programming Language :: Python :: 3.7
Classifier: Programming Language :: Python :: 3.8
Classifier: Programming Language :: Python :: 3.9
Classifier: Programming Language :: Python :: 3.10
Classifier: Programming Language :: Python :: 3.11
Classifier: Programming Language :: Python :: 3.12
Requires-Dist: wson
Project-URL: Repository, https://github.com/lunastev/pipiy
